anarchovk/__init__.py
anarchovk/anarchovk.py
anarchovk-2.0.2.dist-info/LICENSE
anarchovk-2.0.2.dist-info/METADATA
anarchovk-2.0.2.dist-info/WHEEL
anarchovk-2.0.2.dist-info/top_level.txt
anarchovk-2.0.2.dist-info/RECORD
