Metadata-Version: 2.1
Name: anarchovk
Version: 2.0.2
Summary: Easy VK API module for Python
Home-page: https://github.com/dezzev/anarchovk
Author: dezzev
License: ANUS
Platform: UNKNOWN
Classifier: Programming Language :: Python :: 3
Classifier: License :: Public Domain
Classifier: Operating System :: OS Independent
Requires-Python: >=3
Requires-Dist: requests
